{
  "project_info": {
    "project_number": "449354874272",
    "project_id": "activities-c174a",
    "storage_bucket": "activities-c174a.appspot.com"
  },
  "client": [
    {
      "client_info": {
        "mobilesdk_app_id": "1:449354874272:android:fa677e65250ec15b0e38c5",
        "android_client_info": {
          "package_name": "com.galal.activity"
        }
      },
      "oauth_client": [],
      "api_key": [
        {
          "current_key": "AIzaSyCbtAG3DVAl69V5UrXkwneDTlntDq1cpp0"
        }
      ],
      "services": {
        "appinvite_service": {
          "other_platform_oauth_client": []
        }
      }
    }
  ],
  "configuration_version": "1"
}